{
  "difficult": "false",
  "verified": "false",
  "verifier": "None",
  "type": "overworld",
  "steps": 65,
  "population": 29,
  "enemypool": [
    "Siwi",
    "Simi",
    "Optimistick",
    "Pessimistick",
    "Deer God",
    "Oh Deer",
    "Ore Gano",
    "Drizzly Bear",
    "Bayet",
    "Clef"
  ],
  "floors": 1,
  "FloorData": {
    "Floor1": {
      "Room1": "match2",
      "Room2": "stairs"
    },
    "Floor2": {},
    "Floor3": {},
    "Floor4": {},
    "Floor5": {},
    "Floor6": {},
    "Floor7": {},
    "Floor8": {},
    "Floor9": {},
    "Floor10": {}
  },
  "FloorRooms": {
    "Floor1": 2,
    "Floor2": 2,
    "Floor3": 5,
    "Floor4": 4,
    "Floor5": 4,
    "Floor6": 2,
    "Floor7": 2,
    "Floor8": 2,
    "Floor9": 4,
    "Floor10": 5
  },
  "PlayerStats": {
    "HP": 15,
    "ATK": 17,
    "DEF": 5,
    "Lvl": 1,
    "VP": 110
  },
  "Weather": {
    "TempF": -13,
    "TempC": -25,
    "TempStateF": "extreme cold",
    "TempStateC": "extreme cold",
    "Humidity": "mildly dry",
    "Wind": "deadly wind",
    "Season": "Summer",
    "Rain": "light",
    "Conditions": [
      "snow",
      "wind"
    ]
  },
  "CustomEnemy": {
    "HP": 735,
    "ATK": 26,
    "DEF": 17,
    "Lvl": 3
  }
}